sklearn2json/__init__.py
sklearn2json/classification.py
sklearn2json/clustering.py
sklearn2json/common_functions.py
sklearn2json/csr.py
sklearn2json/dimension_reduction.py
sklearn2json/label_encoders.py
sklearn2json/model_selector.py
sklearn2json/regression.py
sklearn2json/vectorizer.py
sklearn2json-2023.2.dist-info/LICENSE.txt
sklearn2json-2023.2.dist-info/METADATA
sklearn2json-2023.2.dist-info/WHEEL
sklearn2json-2023.2.dist-info/RECORD
