Metadata-Version: 2.1
Name: sklearn2json
Version: 2023.2
Summary: Python library for converting Scikit-Learn models to JSON.
License: AGPL
Author: MONTANA Knowledge Management ltd.
Author-email: info@distiller.dev
Requires-Python: >=3.10,<3.11
Classifier: License :: Other/Proprietary License
Classifier: Programming Language :: Python :: 3
Classifier: Programming Language :: Python :: 3.10
Classifier: Topic :: Software Development :: Libraries :: Python Modules
Requires-Dist: scikit-learn (>=1.3.0,<2.0.0)
